serverify.py
serverify_pip-1.0.6.dist-info/LICENSE.txt
serverify_pip-1.0.6.dist-info/METADATA
serverify_pip-1.0.6.dist-info/RECORD
serverify_pip-1.0.6.dist-info/WHEEL
serverify_pip-1.0.6.dist-info/entry_points.txt
serverify_pip-1.0.6.dist-info/top_level.txt
