Metadata-Version: 2.1
Name: serverify-pip
Version: 1.0.6
Summary: Serverify Requirements - export VCS dependencies locally
Home-page: https://github.com/andreif/serverify-pip
Author: Andrei Fokau
Author-email: andrei@5monkeys.se
License: BSD
Download-URL: https://github.com/andreif/serverify-pip/tarball/1.0.6
Keywords: pip,requirements,server,vcs
Platform: UNKNOWN
Classifier: Environment :: Web Environment
Classifier: Natural Language :: English
Classifier: Intended Audience :: Developers
Classifier: License :: OSI Approved :: BSD License
Classifier: Operating System :: OS Independent
Classifier: Programming Language :: Python
Classifier: Programming Language :: Python :: 2
Classifier: Programming Language :: Python :: 2.7
Classifier: Programming Language :: Python :: 3
Classifier: Programming Language :: Python :: 3.4
Classifier: Programming Language :: Python :: 3.5
Classifier: Programming Language :: Python :: 3.6
Classifier: Topic :: Internet :: WWW/HTTP :: Dynamic Content
Classifier: Topic :: Software Development :: Libraries :: Python Modules
Requires-Dist: pip
